{
  "version": 3,
  "middleware": {
    "/": {
      "files": [
        "server/edge/chunks/[root-of-the-server]__6584d596._.js",
        "server/edge/chunks/[root-of-the-server]__dbf8a556._.js",
        "server/edge/chunks/0cd2c_next_dist_esm_build_templates_edge-wrapper_cd939794.js"
      ],
      "name": "middleware",
      "page": "/",
      "matchers": [
        {
          "regexp": "^(?:\\/(_next\\/data\\/[^/]{1,}))?(?:\\/(\\/?index|\\/?index\\\\.json))?[\\/#\\?]?$",
          "originalSource": "/"
        },
        {
          "regexp": "^(?:\\/(_next\\/data\\/[^/]{1,}))?(?:\\/(kk|ru|en))(?:\\/((?:[^\\/#\\?]+?)(?:\\/(?:[^\\/#\\?]+?))*))?(\\\\.json)?[\\/#\\?]?$",
          "originalSource": "/(kk|ru|en)/:path*"
        }
      ],
      "wasm": [],
      "assets": [],
      "env": {
        "__NEXT_BUILD_ID": "kkkUj7X2GO5YTUeVIPt2d",
        "NEXT_SERVER_ACTIONS_ENCRYPTION_KEY": "FlUFQU4y5ak4njrGlWULumSoK7iWSYg10iftfBWXjEs=",
        "__NEXT_PREVIEW_MODE_ID": "0ff0db942f5ac36b8c7043ebd9a3f0b1",
        "__NEXT_PREVIEW_MODE_ENCRYPTION_KEY": "653ccb5fafd3fe79306ee73ab8b78fb28f3bd1905203f612c904c8d8fa86f430",
        "__NEXT_PREVIEW_MODE_SIGNING_KEY": "432047efd5a166541ce08e8d921db6bc9f91038d89f5d6dee65ddb8646978130"
      }
    }
  },
  "sortedMiddleware": [
    "/"
  ],
  "functions": {}
}